CHANGES.txt
LICENSE
MANIFEST.in
README.md
TESTING.txt
pyproject.toml
setup.cfg
setup.py
tox.ini
src/html5lib_to_markdown/__init__.py
src/html5lib_to_markdown/_compat.py
src/html5lib_to_markdown/markdown_info.py
src/html5lib_to_markdown/tokens.py
src/html5lib_to_markdown/transformer.py
src/html5lib_to_markdown/utils.py
src/html5lib_to_markdown.egg-info/PKG-INFO
src/html5lib_to_markdown.egg-info/SOURCES.txt
src/html5lib_to_markdown.egg-info/dependency_links.txt
src/html5lib_to_markdown.egg-info/not-zip-safe
src/html5lib_to_markdown.egg-info/requires.txt
src/html5lib_to_markdown.egg-info/top_level.txt
tests/__init__.py
tests/tests_unit/__init__.py
tests/tests_unit/test_transformations.py
tests/tests_unit/fixtures-transformations/0001-simple.html
tests/tests_unit/fixtures-transformations/0001-simple.md
tests/tests_unit/fixtures-transformations/0002-p_header.html
tests/tests_unit/fixtures-transformations/0002-p_header.md
tests/tests_unit/fixtures-transformations/0003-p_header_alt.html
tests/tests_unit/fixtures-transformations/0003-p_header_alt.md
tests/tests_unit/fixtures-transformations/0004-blockquote_nested_a.html
tests/tests_unit/fixtures-transformations/0004-blockquote_nested_a.md
tests/tests_unit/fixtures-transformations/0005-code.html
tests/tests_unit/fixtures-transformations/0005-code.md
tests/tests_unit/fixtures-transformations/0006-blockquote_nested_lists.html
tests/tests_unit/fixtures-transformations/0006-blockquote_nested_lists.md
tests/tests_unit/fixtures-transformations/0007-ends_on_hr.html
tests/tests_unit/fixtures-transformations/0007-ends_on_hr.md
tests/tests_unit/fixtures-transformations/0008-ends_on_hr_br.html
tests/tests_unit/fixtures-transformations/0008-ends_on_hr_br.md
tests/tests_unit/fixtures-transformations/0009-pre_code_pre.html
tests/tests_unit/fixtures-transformations/0009-pre_code_pre.md
tests/tests_unit/fixtures-transformations/0010-whitespace.html
tests/tests_unit/fixtures-transformations/0010-whitespace.md
tests/tests_unit/fixtures-transformations/0011-blockquote_spacing.html
tests/tests_unit/fixtures-transformations/0011-blockquote_spacing.md
tests/tests_unit/fixtures-transformations/0012-heading.html
tests/tests_unit/fixtures-transformations/0012-heading.md
