Metadata-Version: 2.1
Name: html5lib-to-markdown
Version: 0.0.6
Summary: extract markdown flavored text from html
Home-page: UNKNOWN
Author: Jonathan Vanasco
Author-email: jonathan@findmeon.com
License: UNKNOWN
Platform: UNKNOWN
Classifier: Programming Language :: Python
Classifier: Programming Language :: Python :: 2
Classifier: Programming Language :: Python :: 3
Classifier: Intended Audience :: Developers
Provides-Extra: testing
License-File: LICENSE
